gwtc_analysis/__init__.py
gwtc_analysis/catalogs.py
gwtc_analysis/cli.py
gwtc_analysis/data_repo.py
gwtc_analysis/event_selection.py
gwtc_analysis/gen_readme_cli_tables.py
gwtc_analysis/gw_stat.py
gwtc_analysis/gwpe_utils.py
gwtc_analysis/parameters_estimation.py
gwtc_analysis/read_skymap.py
gwtc_analysis/repo_config.py
gwtc_analysis/report.py
gwtc_analysis/search_skymaps.py
gwtc_analysis-0.3.3.dist-info/licenses/LICENSE
gwtc_analysis-0.3.3.dist-info/METADATA
gwtc_analysis-0.3.3.dist-info/WHEEL
gwtc_analysis-0.3.3.dist-info/entry_points.txt
gwtc_analysis-0.3.3.dist-info/top_level.txt
gwtc_analysis-0.3.3.dist-info/RECORD
