Metadata-Version: 2.4
Name: gwtc_analysis
Version: 0.3.3
Summary: GWTC analysis tool
License: MIT License
Requires-Python: >=3.10
License-File: LICENSE
Requires-Dist: numpy
Requires-Dist: pandas
Requires-Dist: matplotlib
Requires-Dist: minio
Requires-Dist: requests
Dynamic: license-file
